{
 "cells": [
  {
   "cell_type": "code",
   "execution_count": 3,
   "metadata": {
    "collapsed": true
   },
   "outputs": [],
   "source": [
    "import os\n",
    "import sys\n",
    "import dis"
   ]
  },
  {
   "cell_type": "markdown",
   "metadata": {},
   "source": [
    "# The Future: No more bytecode!"
   ]
  },
  {
   "cell_type": "code",
   "execution_count": 4,
   "metadata": {
    "collapsed": false
   },
   "outputs": [
    {
     "name": "stdout",
     "output_type": "stream",
     "text": [
      "3.6.0a2+ (default, Jun 22 2016, 13:01:41) \n",
      "[GCC 6.1.1 20160510 (Red Hat 6.1.1-2)]\n"
     ]
    }
   ],
   "source": [
    "print(sys.version)"
   ]
  },
  {
   "cell_type": "code",
   "execution_count": 5,
   "metadata": {
    "collapsed": false
   },
   "outputs": [
    {
     "name": "stdout",
     "output_type": "stream",
     "text": [
      "a = 3\r\n",
      "b = 'Hello '\r\n",
      "print(a * b)\r\n",
      "\r\n",
      "def func(a=1, *b, **c):\r\n",
      "    return 7 + 3\r\n"
     ]
    }
   ],
   "source": [
    "!cat module.py"
   ]
  },
  {
   "cell_type": "code",
   "execution_count": 6,
   "metadata": {
    "collapsed": false
   },
   "outputs": [
    {
     "name": "stdout",
     "output_type": "stream",
     "text": [
      "  1           0 LOAD_CONST               0 (3)\r\n",
      "              2 STORE_NAME               0 (a)\r\n",
      "\r\n",
      "  2           4 LOAD_CONST               1 ('Hello ')\r\n",
      "              6 STORE_NAME               1 (b)\r\n",
      "\r\n",
      "  3           8 LOAD_NAME                2 (print)\r\n",
      "             10 LOAD_NAME                0 (a)\r\n",
      "             12 LOAD_NAME                1 (b)\r\n",
      "             14 BINARY_MULTIPLY\r\n",
      "             16 CALL_FUNCTION            1 (1 positional, 0 keyword pair)\r\n",
      "             18 POP_TOP\r\n",
      "\r\n",
      "  5          20 LOAD_CONST               6 ((1,))\r\n",
      "             22 LOAD_CONST               3 (<code object func at 0x7f3317b891c0, file \"module.py\", line 5>)\r\n",
      "             24 LOAD_CONST               4 ('func')\r\n",
      "             26 MAKE_FUNCTION            1\r\n",
      "             28 STORE_NAME               3 (func)\r\n",
      "             30 LOAD_CONST               5 (None)\r\n",
      "             32 RETURN_VALUE\r\n"
     ]
    }
   ],
   "source": [
    "!python -m dis module.py"
   ]
  },
  {
   "cell_type": "code",
   "execution_count": 7,
   "metadata": {
    "collapsed": false
   },
   "outputs": [
    {
     "data": {
      "text/plain": [
       "<code object <module> at 0x7fbc842cbd00, file \"/home/pviktori/dev/slides/2016-06-22-pysilesia-bytecode/module.py\", line 1>"
      ]
     },
     "execution_count": 7,
     "metadata": {},
     "output_type": "execute_result"
    }
   ],
   "source": [
    "filename = os.path.abspath('module.py')\n",
    "with open(filename) as f:\n",
    "    code = compile(f.read(), filename=filename, mode='exec')\n",
    "code"
   ]
  },
  {
   "cell_type": "code",
   "execution_count": 8,
   "metadata": {
    "collapsed": false
   },
   "outputs": [
    {
     "name": "stdout",
     "output_type": "stream",
     "text": [
      "[100, 0, 90, 0, 100, 1, 90, 1, 101, 2, 101, 0, 101, 1, 20, 0, 131, 1, 1, 0, 100, 6, 100, 3, 100, 4, 132, 1, 90, 3, 100, 5, 83, 0]\n"
     ]
    }
   ],
   "source": [
    "print(list(code.co_code))"
   ]
  },
  {
   "cell_type": "code",
   "execution_count": 9,
   "metadata": {
    "collapsed": false
   },
   "outputs": [
    {
     "name": "stdout",
     "output_type": "stream",
     "text": [
      "\n",
      " 0:  100      0: LOAD_CONST(3)\n",
      " 2:   90      0: STORE_NAME(a)\n",
      "\n",
      " 4:  100      1: LOAD_CONST('Hello ')\n",
      " 6:   90      1: STORE_NAME(b)\n",
      "\n",
      " 8:  101      2: LOAD_NAME(print)\n",
      "10:  101      0: LOAD_NAME(a)\n",
      "12:  101      1: LOAD_NAME(b)\n",
      "14:   20      -: BINARY_MULTIPLY()\n",
      "16:  131      1: CALL_FUNCTION(1 positional, 0 keyword pair)\n",
      "18:    1      -: POP_TOP()\n",
      "\n",
      "20:  100      6: LOAD_CONST((1,))\n",
      "22:  100      3: LOAD_CONST(<code object func at 0x7fbc85c51400, file \"/home/pviktori/dev/slides/2016-06-22-pysilesia-bytecode/module.py\", line 5>)\n",
      "24:  100      4: LOAD_CONST('func')\n",
      "26:  132      1: MAKE_FUNCTION()\n",
      "28:   90      3: STORE_NAME(func)\n",
      "30:  100      5: LOAD_CONST(None)\n",
      "32:   83      -: RETURN_VALUE()\n"
     ]
    }
   ],
   "source": [
    "def print_dis(code):\n",
    "    line_starts = [a for a, b in dis.findlinestarts(code)]\n",
    "    for instr in dis.get_instructions(code):\n",
    "        if instr.offset in line_starts:\n",
    "            print()\n",
    "        print('{i.offset:2}:  {i.opcode:3} {arg:>6}: {i.opname}({i.argrepr})'.format(\n",
    "                i=instr,\n",
    "                arg='-' if instr.arg is None else instr.arg))\n",
    "\n",
    "print_dis(code)"
   ]
  },
  {
   "cell_type": "markdown",
   "metadata": {},
   "source": [
    "### Summary\n",
    "Starting with Python 3.6, there will be no more bytecode. Python is switching to *wordcode*, where each instruction is two bytes long: a byte for the instruction, and a byte for the argument.\n",
    "The benefit is that wordcode is faster to run: computers are apparently better at handling two-byte units than a mix of one- and three-byte ones.\n",
    "\n",
    "The Python developers are using this opportunity to iron out some warts of the instruction set."
   ]
  },
  {
   "cell_type": "markdown",
   "metadata": {},
   "source": [
    "---\n",
    "# Extra section I - extended arguments"
   ]
  },
  {
   "cell_type": "code",
   "execution_count": 10,
   "metadata": {
    "collapsed": true
   },
   "outputs": [],
   "source": [
    "def print_dis(code):\n",
    "    line_starts = [a for a, b in dis.findlinestarts(code)]\n",
    "    for instr in dis.get_instructions(code):\n",
    "        if instr.offset in line_starts:\n",
    "            print()\n",
    "        print('{i.offset:2}:  {i.opcode:3} {arg:>6}: {i.opname}({i.argrepr})'.format(\n",
    "                i=instr,\n",
    "                arg='-' if instr.arg is None else instr.arg))\n"
   ]
  },
  {
   "cell_type": "code",
   "execution_count": 11,
   "metadata": {
    "collapsed": false
   },
   "outputs": [
    {
     "name": "stdout",
     "output_type": "stream",
     "text": [
      "90 STORE_NAME\n",
      "100 LOAD_CONST\n",
      "144 EXTENDED_ARG\n",
      "\n",
      "[100, 0, 90, 0, 100, 1, 90, 0, 100, 2, 90, 0, 100, 3, 90, 0, 100, 4, 90, 0, 100, 5, 90, 0, 100, 6, 90, 0, 100, 7, 90, 0, 100, 8, 90, 0, 100, 9, 90, 0, 100, 10, 90, 0, 100, 11, 90, 0, 100, 12, 90, 0, 100, 13, 90, 0, 100, 14, 90, 0, 100, 15, 90, 0, 100, 16, 90, 0, 100, 17, 90, 0, 100, 18, 90, 0, 100, 19, 90, 0, 100, 20, 90, 0, 100, 21, 90, 0, 100, 22, 90, 0, 100, 23, 90, 0, 100, 24, 90, 0, 100, 25, 90, 0, 100, 26, 90, 0, 100, 27, 90, 0, 100, 28, 90, 0, 100, 29, 90, 0, 100, 30, 90, 0, 100, 31, 90, 0, 100, 32, 90, 0, 100, 33, 90, 0, 100, 34, 90, 0, 100, 35, 90, 0, 100, 36, 90, 0, 100, 37, 90, 0, 100, 38, 90, 0, 100, 39, 90, 0, 100, 40, 90, 0, 100, 41, 90, 0, 100, 42, 90, 0, 100, 43, 90, 0, 100, 44, 90, 0, 100, 45, 90, 0, 100, 46, 90, 0, 100, 47, 90, 0, 100, 48, 90, 0, 100, 49, 90, 0, 100, 50, 90, 0, 100, 51, 90, 0, 100, 52, 90, 0, 100, 53, 90, 0, 100, 54, 90, 0, 100, 55, 90, 0, 100, 56, 90, 0, 100, 57, 90, 0, 100, 58, 90, 0, 100, 59, 90, 0, 100, 60, 90, 0, 100, 61, 90, 0, 100, 62, 90, 0, 100, 63, 90, 0, 100, 64, 90, 0, 100, 65, 90, 0, 100, 66, 90, 0, 100, 67, 90, 0, 100, 68, 90, 0, 100, 69, 90, 0, 100, 70, 90, 0, 100, 71, 90, 0, 100, 72, 90, 0, 100, 73, 90, 0, 100, 74, 90, 0, 100, 75, 90, 0, 100, 76, 90, 0, 100, 77, 90, 0, 100, 78, 90, 0, 100, 79, 90, 0, 100, 80, 90, 0, 100, 81, 90, 0, 100, 82, 90, 0, 100, 83, 90, 0, 100, 84, 90, 0, 100, 85, 90, 0, 100, 86, 90, 0, 100, 87, 90, 0, 100, 88, 90, 0, 100, 89, 90, 0, 100, 90, 90, 0, 100, 91, 90, 0, 100, 92, 90, 0, 100, 93, 90, 0, 100, 94, 90, 0, 100, 95, 90, 0, 100, 96, 90, 0, 100, 97, 90, 0, 100, 98, 90, 0, 100, 99, 90, 0, 100, 100, 90, 0, 100, 101, 90, 0, 100, 102, 90, 0, 100, 103, 90, 0, 100, 104, 90, 0, 100, 105, 90, 0, 100, 106, 90, 0, 100, 107, 90, 0, 100, 108, 90, 0, 100, 109, 90, 0, 100, 110, 90, 0, 100, 111, 90, 0, 100, 112, 90, 0, 100, 113, 90, 0, 100, 114, 90, 0, 100, 115, 90, 0, 100, 116, 90, 0, 100, 117, 90, 0, 100, 118, 90, 0, 100, 119, 90, 0, 100, 120, 90, 0, 100, 121, 90, 0, 100, 122, 90, 0, 100, 123, 90, 0, 100, 124, 90, 0, 100, 125, 90, 0, 100, 126, 90, 0, 100, 127, 90, 0, 100, 128, 90, 0, 100, 129, 90, 0, 100, 130, 90, 0, 100, 131, 90, 0, 100, 132, 90, 0, 100, 133, 90, 0, 100, 134, 90, 0, 100, 135, 90, 0, 100, 136, 90, 0, 100, 137, 90, 0, 100, 138, 90, 0, 100, 139, 90, 0, 100, 140, 90, 0, 100, 141, 90, 0, 100, 142, 90, 0, 100, 143, 90, 0, 100, 144, 90, 0, 100, 145, 90, 0, 100, 146, 90, 0, 100, 147, 90, 0, 100, 148, 90, 0, 100, 149, 90, 0, 100, 150, 90, 0, 100, 151, 90, 0, 100, 152, 90, 0, 100, 153, 90, 0, 100, 154, 90, 0, 100, 155, 90, 0, 100, 156, 90, 0, 100, 157, 90, 0, 100, 158, 90, 0, 100, 159, 90, 0, 100, 160, 90, 0, 100, 161, 90, 0, 100, 162, 90, 0, 100, 163, 90, 0, 100, 164, 90, 0, 100, 165, 90, 0, 100, 166, 90, 0, 100, 167, 90, 0, 100, 168, 90, 0, 100, 169, 90, 0, 100, 170, 90, 0, 100, 171, 90, 0, 100, 172, 90, 0, 100, 173, 90, 0, 100, 174, 90, 0, 100, 175, 90, 0, 100, 176, 90, 0, 100, 177, 90, 0, 100, 178, 90, 0, 100, 179, 90, 0, 100, 180, 90, 0, 100, 181, 90, 0, 100, 182, 90, 0, 100, 183, 90, 0, 100, 184, 90, 0, 100, 185, 90, 0, 100, 186, 90, 0, 100, 187, 90, 0, 100, 188, 90, 0, 100, 189, 90, 0, 100, 190, 90, 0, 100, 191, 90, 0, 100, 192, 90, 0, 100, 193, 90, 0, 100, 194, 90, 0, 100, 195, 90, 0, 100, 196, 90, 0, 100, 197, 90, 0, 100, 198, 90, 0, 100, 199, 90, 0, 100, 200, 90, 0, 100, 201, 90, 0, 100, 202, 90, 0, 100, 203, 90, 0, 100, 204, 90, 0, 100, 205, 90, 0, 100, 206, 90, 0, 100, 207, 90, 0, 100, 208, 90, 0, 100, 209, 90, 0, 100, 210, 90, 0, 100, 211, 90, 0, 100, 212, 90, 0, 100, 213, 90, 0, 100, 214, 90, 0, 100, 215, 90, 0, 100, 216, 90, 0, 100, 217, 90, 0, 100, 218, 90, 0, 100, 219, 90, 0, 100, 220, 90, 0, 100, 221, 90, 0, 100, 222, 90, 0, 100, 223, 90, 0, 100, 224, 90, 0, 100, 225, 90, 0, 100, 226, 90, 0, 100, 227, 90, 0, 100, 228, 90, 0, 100, 229, 90, 0, 100, 230, 90, 0, 100, 231, 90, 0, 100, 232, 90, 0, 100, 233, 90, 0, 100, 234, 90, 0, 100, 235, 90, 0, 100, 236, 90, 0, 100, 237, 90, 0, 100, 238, 90, 0, 100, 239, 90, 0, 100, 240, 90, 0, 100, 241, 90, 0, 100, 242, 90, 0, 100, 243, 90, 0, 100, 244, 90, 0, 100, 245, 90, 0, 100, 246, 90, 0, 100, 247, 90, 0, 100, 248, 90, 0, 100, 249, 90, 0, 100, 250, 90, 0, 100, 251, 90, 0, 100, 252, 90, 0, 100, 253, 90, 0, 100, 254, 90, 0, 100, 255, 90, 0, 144, 1, 100, 0, 90, 0, 144, 1, 100, 1, 90, 0, 144, 1, 100, 2, 90, 0, 144, 1, 100, 3, 90, 0, 144, 1, 100, 4, 83, 0]\n",
      "\n",
      " 0:  100      0: LOAD_CONST(0)\n",
      " 2:   90      0: STORE_NAME(a)\n",
      "\n",
      " 4:  100      1: LOAD_CONST(1)\n",
      " 6:   90      0: STORE_NAME(a)\n",
      "\n",
      " 8:  100      2: LOAD_CONST(2)\n",
      "10:   90      0: STORE_NAME(a)\n",
      "\n",
      "12:  100      3: LOAD_CONST(3)\n",
      "14:   90      0: STORE_NAME(a)\n",
      "\n",
      "16:  100      4: LOAD_CONST(4)\n",
      "18:   90      0: STORE_NAME(a)\n",
      "\n",
      "20:  100      5: LOAD_CONST(5)\n",
      "22:   90      0: STORE_NAME(a)\n",
      "\n",
      "24:  100      6: LOAD_CONST(6)\n",
      "26:   90      0: STORE_NAME(a)\n",
      "\n",
      "28:  100      7: LOAD_CONST(7)\n",
      "30:   90      0: STORE_NAME(a)\n",
      "\n",
      "32:  100      8: LOAD_CONST(8)\n",
      "34:   90      0: STORE_NAME(a)\n",
      "\n",
      "36:  100      9: LOAD_CONST(9)\n",
      "38:   90      0: STORE_NAME(a)\n",
      "\n",
      "40:  100     10: LOAD_CONST(10)\n",
      "42:   90      0: STORE_NAME(a)\n",
      "\n",
      "44:  100     11: LOAD_CONST(11)\n",
      "46:   90      0: STORE_NAME(a)\n",
      "\n",
      "48:  100     12: LOAD_CONST(12)\n",
      "50:   90      0: STORE_NAME(a)\n",
      "\n",
      "52:  100     13: LOAD_CONST(13)\n",
      "54:   90      0: STORE_NAME(a)\n",
      "\n",
      "56:  100     14: LOAD_CONST(14)\n",
      "58:   90      0: STORE_NAME(a)\n",
      "\n",
      "60:  100     15: LOAD_CONST(15)\n",
      "62:   90      0: STORE_NAME(a)\n",
      "\n",
      "64:  100     16: LOAD_CONST(16)\n",
      "66:   90      0: STORE_NAME(a)\n",
      "\n",
      "68:  100     17: LOAD_CONST(17)\n",
      "70:   90      0: STORE_NAME(a)\n",
      "\n",
      "72:  100     18: LOAD_CONST(18)\n",
      "74:   90      0: STORE_NAME(a)\n",
      "\n",
      "76:  100     19: LOAD_CONST(19)\n",
      "78:   90      0: STORE_NAME(a)\n",
      "\n",
      "80:  100     20: LOAD_CONST(20)\n",
      "82:   90      0: STORE_NAME(a)\n",
      "\n",
      "84:  100     21: LOAD_CONST(21)\n",
      "86:   90      0: STORE_NAME(a)\n",
      "\n",
      "88:  100     22: LOAD_CONST(22)\n",
      "90:   90      0: STORE_NAME(a)\n",
      "\n",
      "92:  100     23: LOAD_CONST(23)\n",
      "94:   90      0: STORE_NAME(a)\n",
      "\n",
      "96:  100     24: LOAD_CONST(24)\n",
      "98:   90      0: STORE_NAME(a)\n",
      "\n",
      "100:  100     25: LOAD_CONST(25)\n",
      "102:   90      0: STORE_NAME(a)\n",
      "\n",
      "104:  100     26: LOAD_CONST(26)\n",
      "106:   90      0: STORE_NAME(a)\n",
      "\n",
      "108:  100     27: LOAD_CONST(27)\n",
      "110:   90      0: STORE_NAME(a)\n",
      "\n",
      "112:  100     28: LOAD_CONST(28)\n",
      "114:   90      0: STORE_NAME(a)\n",
      "\n",
      "116:  100     29: LOAD_CONST(29)\n",
      "118:   90      0: STORE_NAME(a)\n",
      "\n",
      "120:  100     30: LOAD_CONST(30)\n",
      "122:   90      0: STORE_NAME(a)\n",
      "\n",
      "124:  100     31: LOAD_CONST(31)\n",
      "126:   90      0: STORE_NAME(a)\n",
      "\n",
      "128:  100     32: LOAD_CONST(32)\n",
      "130:   90      0: STORE_NAME(a)\n",
      "\n",
      "132:  100     33: LOAD_CONST(33)\n",
      "134:   90      0: STORE_NAME(a)\n",
      "\n",
      "136:  100     34: LOAD_CONST(34)\n",
      "138:   90      0: STORE_NAME(a)\n",
      "\n",
      "140:  100     35: LOAD_CONST(35)\n",
      "142:   90      0: STORE_NAME(a)\n",
      "\n",
      "144:  100     36: LOAD_CONST(36)\n",
      "146:   90      0: STORE_NAME(a)\n",
      "\n",
      "148:  100     37: LOAD_CONST(37)\n",
      "150:   90      0: STORE_NAME(a)\n",
      "\n",
      "152:  100     38: LOAD_CONST(38)\n",
      "154:   90      0: STORE_NAME(a)\n",
      "\n",
      "156:  100     39: LOAD_CONST(39)\n",
      "158:   90      0: STORE_NAME(a)\n",
      "\n",
      "160:  100     40: LOAD_CONST(40)\n",
      "162:   90      0: STORE_NAME(a)\n",
      "\n",
      "164:  100     41: LOAD_CONST(41)\n",
      "166:   90      0: STORE_NAME(a)\n",
      "\n",
      "168:  100     42: LOAD_CONST(42)\n",
      "170:   90      0: STORE_NAME(a)\n",
      "\n",
      "172:  100     43: LOAD_CONST(43)\n",
      "174:   90      0: STORE_NAME(a)\n",
      "\n",
      "176:  100     44: LOAD_CONST(44)\n",
      "178:   90      0: STORE_NAME(a)\n",
      "\n",
      "180:  100     45: LOAD_CONST(45)\n",
      "182:   90      0: STORE_NAME(a)\n",
      "\n",
      "184:  100     46: LOAD_CONST(46)\n",
      "186:   90      0: STORE_NAME(a)\n",
      "\n",
      "188:  100     47: LOAD_CONST(47)\n",
      "190:   90      0: STORE_NAME(a)\n",
      "\n",
      "192:  100     48: LOAD_CONST(48)\n",
      "194:   90      0: STORE_NAME(a)\n",
      "\n",
      "196:  100     49: LOAD_CONST(49)\n",
      "198:   90      0: STORE_NAME(a)\n",
      "\n",
      "200:  100     50: LOAD_CONST(50)\n",
      "202:   90      0: STORE_NAME(a)\n",
      "\n",
      "204:  100     51: LOAD_CONST(51)\n",
      "206:   90      0: STORE_NAME(a)\n",
      "\n",
      "208:  100     52: LOAD_CONST(52)\n",
      "210:   90      0: STORE_NAME(a)\n",
      "\n",
      "212:  100     53: LOAD_CONST(53)\n",
      "214:   90      0: STORE_NAME(a)\n",
      "\n",
      "216:  100     54: LOAD_CONST(54)\n",
      "218:   90      0: STORE_NAME(a)\n",
      "\n",
      "220:  100     55: LOAD_CONST(55)\n",
      "222:   90      0: STORE_NAME(a)\n",
      "\n",
      "224:  100     56: LOAD_CONST(56)\n",
      "226:   90      0: STORE_NAME(a)\n",
      "\n",
      "228:  100     57: LOAD_CONST(57)\n",
      "230:   90      0: STORE_NAME(a)\n",
      "\n",
      "232:  100     58: LOAD_CONST(58)\n",
      "234:   90      0: STORE_NAME(a)\n",
      "\n",
      "236:  100     59: LOAD_CONST(59)\n",
      "238:   90      0: STORE_NAME(a)\n",
      "\n",
      "240:  100     60: LOAD_CONST(60)\n",
      "242:   90      0: STORE_NAME(a)\n",
      "\n",
      "244:  100     61: LOAD_CONST(61)\n",
      "246:   90      0: STORE_NAME(a)\n",
      "\n",
      "248:  100     62: LOAD_CONST(62)\n",
      "250:   90      0: STORE_NAME(a)\n",
      "\n",
      "252:  100     63: LOAD_CONST(63)\n",
      "254:   90      0: STORE_NAME(a)\n",
      "\n",
      "256:  100     64: LOAD_CONST(64)\n",
      "258:   90      0: STORE_NAME(a)\n",
      "\n",
      "260:  100     65: LOAD_CONST(65)\n",
      "262:   90      0: STORE_NAME(a)\n",
      "\n",
      "264:  100     66: LOAD_CONST(66)\n",
      "266:   90      0: STORE_NAME(a)\n",
      "\n",
      "268:  100     67: LOAD_CONST(67)\n",
      "270:   90      0: STORE_NAME(a)\n",
      "\n",
      "272:  100     68: LOAD_CONST(68)\n",
      "274:   90      0: STORE_NAME(a)\n",
      "\n",
      "276:  100     69: LOAD_CONST(69)\n",
      "278:   90      0: STORE_NAME(a)\n",
      "\n",
      "280:  100     70: LOAD_CONST(70)\n",
      "282:   90      0: STORE_NAME(a)\n",
      "\n",
      "284:  100     71: LOAD_CONST(71)\n",
      "286:   90      0: STORE_NAME(a)\n",
      "\n",
      "288:  100     72: LOAD_CONST(72)\n",
      "290:   90      0: STORE_NAME(a)\n",
      "\n",
      "292:  100     73: LOAD_CONST(73)\n",
      "294:   90      0: STORE_NAME(a)\n",
      "\n",
      "296:  100     74: LOAD_CONST(74)\n",
      "298:   90      0: STORE_NAME(a)\n",
      "\n",
      "300:  100     75: LOAD_CONST(75)\n",
      "302:   90      0: STORE_NAME(a)\n",
      "\n",
      "304:  100     76: LOAD_CONST(76)\n",
      "306:   90      0: STORE_NAME(a)\n",
      "\n",
      "308:  100     77: LOAD_CONST(77)\n",
      "310:   90      0: STORE_NAME(a)\n",
      "\n",
      "312:  100     78: LOAD_CONST(78)\n",
      "314:   90      0: STORE_NAME(a)\n",
      "\n",
      "316:  100     79: LOAD_CONST(79)\n",
      "318:   90      0: STORE_NAME(a)\n",
      "\n",
      "320:  100     80: LOAD_CONST(80)\n",
      "322:   90      0: STORE_NAME(a)\n",
      "\n",
      "324:  100     81: LOAD_CONST(81)\n",
      "326:   90      0: STORE_NAME(a)\n",
      "\n",
      "328:  100     82: LOAD_CONST(82)\n",
      "330:   90      0: STORE_NAME(a)\n",
      "\n",
      "332:  100     83: LOAD_CONST(83)\n",
      "334:   90      0: STORE_NAME(a)\n",
      "\n",
      "336:  100     84: LOAD_CONST(84)\n",
      "338:   90      0: STORE_NAME(a)\n",
      "\n",
      "340:  100     85: LOAD_CONST(85)\n",
      "342:   90      0: STORE_NAME(a)\n",
      "\n",
      "344:  100     86: LOAD_CONST(86)\n",
      "346:   90      0: STORE_NAME(a)\n",
      "\n",
      "348:  100     87: LOAD_CONST(87)\n",
      "350:   90      0: STORE_NAME(a)\n",
      "\n",
      "352:  100     88: LOAD_CONST(88)\n",
      "354:   90      0: STORE_NAME(a)\n",
      "\n",
      "356:  100     89: LOAD_CONST(89)\n",
      "358:   90      0: STORE_NAME(a)\n",
      "\n",
      "360:  100     90: LOAD_CONST(90)\n",
      "362:   90      0: STORE_NAME(a)\n",
      "\n",
      "364:  100     91: LOAD_CONST(91)\n",
      "366:   90      0: STORE_NAME(a)\n",
      "\n",
      "368:  100     92: LOAD_CONST(92)\n",
      "370:   90      0: STORE_NAME(a)\n",
      "\n",
      "372:  100     93: LOAD_CONST(93)\n",
      "374:   90      0: STORE_NAME(a)\n",
      "\n",
      "376:  100     94: LOAD_CONST(94)\n",
      "378:   90      0: STORE_NAME(a)\n",
      "\n",
      "380:  100     95: LOAD_CONST(95)\n",
      "382:   90      0: STORE_NAME(a)\n",
      "\n",
      "384:  100     96: LOAD_CONST(96)\n",
      "386:   90      0: STORE_NAME(a)\n",
      "\n",
      "388:  100     97: LOAD_CONST(97)\n",
      "390:   90      0: STORE_NAME(a)\n",
      "\n",
      "392:  100     98: LOAD_CONST(98)\n",
      "394:   90      0: STORE_NAME(a)\n",
      "\n",
      "396:  100     99: LOAD_CONST(99)\n",
      "398:   90      0: STORE_NAME(a)\n",
      "\n",
      "400:  100    100: LOAD_CONST(100)\n",
      "402:   90      0: STORE_NAME(a)\n",
      "\n",
      "404:  100    101: LOAD_CONST(101)\n",
      "406:   90      0: STORE_NAME(a)\n",
      "\n",
      "408:  100    102: LOAD_CONST(102)\n",
      "410:   90      0: STORE_NAME(a)\n",
      "\n",
      "412:  100    103: LOAD_CONST(103)\n",
      "414:   90      0: STORE_NAME(a)\n",
      "\n",
      "416:  100    104: LOAD_CONST(104)\n",
      "418:   90      0: STORE_NAME(a)\n",
      "\n",
      "420:  100    105: LOAD_CONST(105)\n",
      "422:   90      0: STORE_NAME(a)\n",
      "\n",
      "424:  100    106: LOAD_CONST(106)\n",
      "426:   90      0: STORE_NAME(a)\n",
      "\n",
      "428:  100    107: LOAD_CONST(107)\n",
      "430:   90      0: STORE_NAME(a)\n",
      "\n",
      "432:  100    108: LOAD_CONST(108)\n",
      "434:   90      0: STORE_NAME(a)\n",
      "\n",
      "436:  100    109: LOAD_CONST(109)\n",
      "438:   90      0: STORE_NAME(a)\n",
      "\n",
      "440:  100    110: LOAD_CONST(110)\n",
      "442:   90      0: STORE_NAME(a)\n",
      "\n",
      "444:  100    111: LOAD_CONST(111)\n",
      "446:   90      0: STORE_NAME(a)\n",
      "\n",
      "448:  100    112: LOAD_CONST(112)\n",
      "450:   90      0: STORE_NAME(a)\n",
      "\n",
      "452:  100    113: LOAD_CONST(113)\n",
      "454:   90      0: STORE_NAME(a)\n",
      "\n",
      "456:  100    114: LOAD_CONST(114)\n",
      "458:   90      0: STORE_NAME(a)\n",
      "\n",
      "460:  100    115: LOAD_CONST(115)\n",
      "462:   90      0: STORE_NAME(a)\n",
      "\n",
      "464:  100    116: LOAD_CONST(116)\n",
      "466:   90      0: STORE_NAME(a)\n",
      "\n",
      "468:  100    117: LOAD_CONST(117)\n",
      "470:   90      0: STORE_NAME(a)\n",
      "\n",
      "472:  100    118: LOAD_CONST(118)\n",
      "474:   90      0: STORE_NAME(a)\n",
      "\n",
      "476:  100    119: LOAD_CONST(119)\n",
      "478:   90      0: STORE_NAME(a)\n",
      "\n",
      "480:  100    120: LOAD_CONST(120)\n",
      "482:   90      0: STORE_NAME(a)\n",
      "\n",
      "484:  100    121: LOAD_CONST(121)\n",
      "486:   90      0: STORE_NAME(a)\n",
      "\n",
      "488:  100    122: LOAD_CONST(122)\n",
      "490:   90      0: STORE_NAME(a)\n",
      "\n",
      "492:  100    123: LOAD_CONST(123)\n",
      "494:   90      0: STORE_NAME(a)\n",
      "\n",
      "496:  100    124: LOAD_CONST(124)\n",
      "498:   90      0: STORE_NAME(a)\n",
      "\n",
      "500:  100    125: LOAD_CONST(125)\n",
      "502:   90      0: STORE_NAME(a)\n",
      "\n",
      "504:  100    126: LOAD_CONST(126)\n",
      "506:   90      0: STORE_NAME(a)\n",
      "\n",
      "508:  100    127: LOAD_CONST(127)\n",
      "510:   90      0: STORE_NAME(a)\n",
      "\n",
      "512:  100    128: LOAD_CONST(128)\n",
      "514:   90      0: STORE_NAME(a)\n",
      "\n",
      "516:  100    129: LOAD_CONST(129)\n",
      "518:   90      0: STORE_NAME(a)\n",
      "\n",
      "520:  100    130: LOAD_CONST(130)\n",
      "522:   90      0: STORE_NAME(a)\n",
      "\n",
      "524:  100    131: LOAD_CONST(131)\n",
      "526:   90      0: STORE_NAME(a)\n",
      "\n",
      "528:  100    132: LOAD_CONST(132)\n",
      "530:   90      0: STORE_NAME(a)\n",
      "\n",
      "532:  100    133: LOAD_CONST(133)\n",
      "534:   90      0: STORE_NAME(a)\n",
      "\n",
      "536:  100    134: LOAD_CONST(134)\n",
      "538:   90      0: STORE_NAME(a)\n",
      "\n",
      "540:  100    135: LOAD_CONST(135)\n",
      "542:   90      0: STORE_NAME(a)\n",
      "\n",
      "544:  100    136: LOAD_CONST(136)\n",
      "546:   90      0: STORE_NAME(a)\n",
      "\n",
      "548:  100    137: LOAD_CONST(137)\n",
      "550:   90      0: STORE_NAME(a)\n",
      "\n",
      "552:  100    138: LOAD_CONST(138)\n",
      "554:   90      0: STORE_NAME(a)\n",
      "\n",
      "556:  100    139: LOAD_CONST(139)\n",
      "558:   90      0: STORE_NAME(a)\n",
      "\n",
      "560:  100    140: LOAD_CONST(140)\n",
      "562:   90      0: STORE_NAME(a)\n",
      "\n",
      "564:  100    141: LOAD_CONST(141)\n",
      "566:   90      0: STORE_NAME(a)\n",
      "\n",
      "568:  100    142: LOAD_CONST(142)\n",
      "570:   90      0: STORE_NAME(a)\n",
      "\n",
      "572:  100    143: LOAD_CONST(143)\n",
      "574:   90      0: STORE_NAME(a)\n",
      "\n",
      "576:  100    144: LOAD_CONST(144)\n",
      "578:   90      0: STORE_NAME(a)\n",
      "\n",
      "580:  100    145: LOAD_CONST(145)\n",
      "582:   90      0: STORE_NAME(a)\n",
      "\n",
      "584:  100    146: LOAD_CONST(146)\n",
      "586:   90      0: STORE_NAME(a)\n",
      "\n",
      "588:  100    147: LOAD_CONST(147)\n",
      "590:   90      0: STORE_NAME(a)\n",
      "\n",
      "592:  100    148: LOAD_CONST(148)\n",
      "594:   90      0: STORE_NAME(a)\n",
      "\n",
      "596:  100    149: LOAD_CONST(149)\n",
      "598:   90      0: STORE_NAME(a)\n",
      "\n",
      "600:  100    150: LOAD_CONST(150)\n",
      "602:   90      0: STORE_NAME(a)\n",
      "\n",
      "604:  100    151: LOAD_CONST(151)\n",
      "606:   90      0: STORE_NAME(a)\n",
      "\n",
      "608:  100    152: LOAD_CONST(152)\n",
      "610:   90      0: STORE_NAME(a)\n",
      "\n",
      "612:  100    153: LOAD_CONST(153)\n",
      "614:   90      0: STORE_NAME(a)\n",
      "\n",
      "616:  100    154: LOAD_CONST(154)\n",
      "618:   90      0: STORE_NAME(a)\n",
      "\n",
      "620:  100    155: LOAD_CONST(155)\n",
      "622:   90      0: STORE_NAME(a)\n",
      "\n",
      "624:  100    156: LOAD_CONST(156)\n",
      "626:   90      0: STORE_NAME(a)\n",
      "\n",
      "628:  100    157: LOAD_CONST(157)\n",
      "630:   90      0: STORE_NAME(a)\n",
      "\n",
      "632:  100    158: LOAD_CONST(158)\n",
      "634:   90      0: STORE_NAME(a)\n",
      "\n",
      "636:  100    159: LOAD_CONST(159)\n",
      "638:   90      0: STORE_NAME(a)\n",
      "\n",
      "640:  100    160: LOAD_CONST(160)\n",
      "642:   90      0: STORE_NAME(a)\n",
      "\n",
      "644:  100    161: LOAD_CONST(161)\n",
      "646:   90      0: STORE_NAME(a)\n",
      "\n",
      "648:  100    162: LOAD_CONST(162)\n",
      "650:   90      0: STORE_NAME(a)\n",
      "\n",
      "652:  100    163: LOAD_CONST(163)\n",
      "654:   90      0: STORE_NAME(a)\n",
      "\n",
      "656:  100    164: LOAD_CONST(164)\n",
      "658:   90      0: STORE_NAME(a)\n",
      "\n",
      "660:  100    165: LOAD_CONST(165)\n",
      "662:   90      0: STORE_NAME(a)\n",
      "\n",
      "664:  100    166: LOAD_CONST(166)\n",
      "666:   90      0: STORE_NAME(a)\n",
      "\n",
      "668:  100    167: LOAD_CONST(167)\n",
      "670:   90      0: STORE_NAME(a)\n",
      "\n",
      "672:  100    168: LOAD_CONST(168)\n",
      "674:   90      0: STORE_NAME(a)\n",
      "\n",
      "676:  100    169: LOAD_CONST(169)\n",
      "678:   90      0: STORE_NAME(a)\n",
      "\n",
      "680:  100    170: LOAD_CONST(170)\n",
      "682:   90      0: STORE_NAME(a)\n",
      "\n",
      "684:  100    171: LOAD_CONST(171)\n",
      "686:   90      0: STORE_NAME(a)\n",
      "\n",
      "688:  100    172: LOAD_CONST(172)\n",
      "690:   90      0: STORE_NAME(a)\n",
      "\n",
      "692:  100    173: LOAD_CONST(173)\n",
      "694:   90      0: STORE_NAME(a)\n",
      "\n",
      "696:  100    174: LOAD_CONST(174)\n",
      "698:   90      0: STORE_NAME(a)\n",
      "\n",
      "700:  100    175: LOAD_CONST(175)\n",
      "702:   90      0: STORE_NAME(a)\n",
      "\n",
      "704:  100    176: LOAD_CONST(176)\n",
      "706:   90      0: STORE_NAME(a)\n",
      "\n",
      "708:  100    177: LOAD_CONST(177)\n",
      "710:   90      0: STORE_NAME(a)\n",
      "\n",
      "712:  100    178: LOAD_CONST(178)\n",
      "714:   90      0: STORE_NAME(a)\n",
      "\n",
      "716:  100    179: LOAD_CONST(179)\n",
      "718:   90      0: STORE_NAME(a)\n",
      "\n",
      "720:  100    180: LOAD_CONST(180)\n",
      "722:   90      0: STORE_NAME(a)\n",
      "\n",
      "724:  100    181: LOAD_CONST(181)\n",
      "726:   90      0: STORE_NAME(a)\n",
      "\n",
      "728:  100    182: LOAD_CONST(182)\n",
      "730:   90      0: STORE_NAME(a)\n",
      "\n",
      "732:  100    183: LOAD_CONST(183)\n",
      "734:   90      0: STORE_NAME(a)\n",
      "\n",
      "736:  100    184: LOAD_CONST(184)\n",
      "738:   90      0: STORE_NAME(a)\n",
      "\n",
      "740:  100    185: LOAD_CONST(185)\n",
      "742:   90      0: STORE_NAME(a)\n",
      "\n",
      "744:  100    186: LOAD_CONST(186)\n",
      "746:   90      0: STORE_NAME(a)\n",
      "\n",
      "748:  100    187: LOAD_CONST(187)\n",
      "750:   90      0: STORE_NAME(a)\n",
      "\n",
      "752:  100    188: LOAD_CONST(188)\n",
      "754:   90      0: STORE_NAME(a)\n",
      "\n",
      "756:  100    189: LOAD_CONST(189)\n",
      "758:   90      0: STORE_NAME(a)\n",
      "\n",
      "760:  100    190: LOAD_CONST(190)\n",
      "762:   90      0: STORE_NAME(a)\n",
      "\n",
      "764:  100    191: LOAD_CONST(191)\n",
      "766:   90      0: STORE_NAME(a)\n",
      "\n",
      "768:  100    192: LOAD_CONST(192)\n",
      "770:   90      0: STORE_NAME(a)\n",
      "\n",
      "772:  100    193: LOAD_CONST(193)\n",
      "774:   90      0: STORE_NAME(a)\n",
      "\n",
      "776:  100    194: LOAD_CONST(194)\n",
      "778:   90      0: STORE_NAME(a)\n",
      "\n",
      "780:  100    195: LOAD_CONST(195)\n",
      "782:   90      0: STORE_NAME(a)\n",
      "\n",
      "784:  100    196: LOAD_CONST(196)\n",
      "786:   90      0: STORE_NAME(a)\n",
      "\n",
      "788:  100    197: LOAD_CONST(197)\n",
      "790:   90      0: STORE_NAME(a)\n",
      "\n",
      "792:  100    198: LOAD_CONST(198)\n",
      "794:   90      0: STORE_NAME(a)\n",
      "\n",
      "796:  100    199: LOAD_CONST(199)\n",
      "798:   90      0: STORE_NAME(a)\n",
      "\n",
      "800:  100    200: LOAD_CONST(200)\n",
      "802:   90      0: STORE_NAME(a)\n",
      "\n",
      "804:  100    201: LOAD_CONST(201)\n",
      "806:   90      0: STORE_NAME(a)\n",
      "\n",
      "808:  100    202: LOAD_CONST(202)\n",
      "810:   90      0: STORE_NAME(a)\n",
      "\n",
      "812:  100    203: LOAD_CONST(203)\n",
      "814:   90      0: STORE_NAME(a)\n",
      "\n",
      "816:  100    204: LOAD_CONST(204)\n",
      "818:   90      0: STORE_NAME(a)\n",
      "\n",
      "820:  100    205: LOAD_CONST(205)\n",
      "822:   90      0: STORE_NAME(a)\n",
      "\n",
      "824:  100    206: LOAD_CONST(206)\n",
      "826:   90      0: STORE_NAME(a)\n",
      "\n",
      "828:  100    207: LOAD_CONST(207)\n",
      "830:   90      0: STORE_NAME(a)\n",
      "\n",
      "832:  100    208: LOAD_CONST(208)\n",
      "834:   90      0: STORE_NAME(a)\n",
      "\n",
      "836:  100    209: LOAD_CONST(209)\n",
      "838:   90      0: STORE_NAME(a)\n",
      "\n",
      "840:  100    210: LOAD_CONST(210)\n",
      "842:   90      0: STORE_NAME(a)\n",
      "\n",
      "844:  100    211: LOAD_CONST(211)\n",
      "846:   90      0: STORE_NAME(a)\n",
      "\n",
      "848:  100    212: LOAD_CONST(212)\n",
      "850:   90      0: STORE_NAME(a)\n",
      "\n",
      "852:  100    213: LOAD_CONST(213)\n",
      "854:   90      0: STORE_NAME(a)\n",
      "\n",
      "856:  100    214: LOAD_CONST(214)\n",
      "858:   90      0: STORE_NAME(a)\n",
      "\n",
      "860:  100    215: LOAD_CONST(215)\n",
      "862:   90      0: STORE_NAME(a)\n",
      "\n",
      "864:  100    216: LOAD_CONST(216)\n",
      "866:   90      0: STORE_NAME(a)\n",
      "\n",
      "868:  100    217: LOAD_CONST(217)\n",
      "870:   90      0: STORE_NAME(a)\n",
      "\n",
      "872:  100    218: LOAD_CONST(218)\n",
      "874:   90      0: STORE_NAME(a)\n",
      "\n",
      "876:  100    219: LOAD_CONST(219)\n",
      "878:   90      0: STORE_NAME(a)\n",
      "\n",
      "880:  100    220: LOAD_CONST(220)\n",
      "882:   90      0: STORE_NAME(a)\n",
      "\n",
      "884:  100    221: LOAD_CONST(221)\n",
      "886:   90      0: STORE_NAME(a)\n",
      "\n",
      "888:  100    222: LOAD_CONST(222)\n",
      "890:   90      0: STORE_NAME(a)\n",
      "\n",
      "892:  100    223: LOAD_CONST(223)\n",
      "894:   90      0: STORE_NAME(a)\n",
      "\n",
      "896:  100    224: LOAD_CONST(224)\n",
      "898:   90      0: STORE_NAME(a)\n",
      "\n",
      "900:  100    225: LOAD_CONST(225)\n",
      "902:   90      0: STORE_NAME(a)\n",
      "\n",
      "904:  100    226: LOAD_CONST(226)\n",
      "906:   90      0: STORE_NAME(a)\n",
      "\n",
      "908:  100    227: LOAD_CONST(227)\n",
      "910:   90      0: STORE_NAME(a)\n",
      "\n",
      "912:  100    228: LOAD_CONST(228)\n",
      "914:   90      0: STORE_NAME(a)\n",
      "\n",
      "916:  100    229: LOAD_CONST(229)\n",
      "918:   90      0: STORE_NAME(a)\n",
      "\n",
      "920:  100    230: LOAD_CONST(230)\n",
      "922:   90      0: STORE_NAME(a)\n",
      "\n",
      "924:  100    231: LOAD_CONST(231)\n",
      "926:   90      0: STORE_NAME(a)\n",
      "\n",
      "928:  100    232: LOAD_CONST(232)\n",
      "930:   90      0: STORE_NAME(a)\n",
      "\n",
      "932:  100    233: LOAD_CONST(233)\n",
      "934:   90      0: STORE_NAME(a)\n",
      "\n",
      "936:  100    234: LOAD_CONST(234)\n",
      "938:   90      0: STORE_NAME(a)\n",
      "\n",
      "940:  100    235: LOAD_CONST(235)\n",
      "942:   90      0: STORE_NAME(a)\n",
      "\n",
      "944:  100    236: LOAD_CONST(236)\n",
      "946:   90      0: STORE_NAME(a)\n",
      "\n",
      "948:  100    237: LOAD_CONST(237)\n",
      "950:   90      0: STORE_NAME(a)\n",
      "\n",
      "952:  100    238: LOAD_CONST(238)\n",
      "954:   90      0: STORE_NAME(a)\n",
      "\n",
      "956:  100    239: LOAD_CONST(239)\n",
      "958:   90      0: STORE_NAME(a)\n",
      "\n",
      "960:  100    240: LOAD_CONST(240)\n",
      "962:   90      0: STORE_NAME(a)\n",
      "\n",
      "964:  100    241: LOAD_CONST(241)\n",
      "966:   90      0: STORE_NAME(a)\n",
      "\n",
      "968:  100    242: LOAD_CONST(242)\n",
      "970:   90      0: STORE_NAME(a)\n",
      "\n",
      "972:  100    243: LOAD_CONST(243)\n",
      "974:   90      0: STORE_NAME(a)\n",
      "\n",
      "976:  100    244: LOAD_CONST(244)\n",
      "978:   90      0: STORE_NAME(a)\n",
      "\n",
      "980:  100    245: LOAD_CONST(245)\n",
      "982:   90      0: STORE_NAME(a)\n",
      "\n",
      "984:  100    246: LOAD_CONST(246)\n",
      "986:   90      0: STORE_NAME(a)\n",
      "\n",
      "988:  100    247: LOAD_CONST(247)\n",
      "990:   90      0: STORE_NAME(a)\n",
      "\n",
      "992:  100    248: LOAD_CONST(248)\n",
      "994:   90      0: STORE_NAME(a)\n",
      "\n",
      "996:  100    249: LOAD_CONST(249)\n",
      "998:   90      0: STORE_NAME(a)\n",
      "\n",
      "1000:  100    250: LOAD_CONST(250)\n",
      "1002:   90      0: STORE_NAME(a)\n",
      "\n",
      "1004:  100    251: LOAD_CONST(251)\n",
      "1006:   90      0: STORE_NAME(a)\n",
      "\n",
      "1008:  100    252: LOAD_CONST(252)\n",
      "1010:   90      0: STORE_NAME(a)\n",
      "\n",
      "1012:  100    253: LOAD_CONST(253)\n",
      "1014:   90      0: STORE_NAME(a)\n",
      "\n",
      "1016:  100    254: LOAD_CONST(254)\n",
      "1018:   90      0: STORE_NAME(a)\n",
      "\n",
      "1020:  100    255: LOAD_CONST(255)\n",
      "1022:   90      0: STORE_NAME(a)\n",
      "\n",
      "1024:  144      1: EXTENDED_ARG()\n",
      "1026:  100    256: LOAD_CONST(256)\n",
      "1028:   90      0: STORE_NAME(a)\n",
      "\n",
      "1030:  144      1: EXTENDED_ARG()\n",
      "1032:  100    257: LOAD_CONST(257)\n",
      "1034:   90      0: STORE_NAME(a)\n",
      "\n",
      "1036:  144      1: EXTENDED_ARG()\n",
      "1038:  100    258: LOAD_CONST(258)\n",
      "1040:   90      0: STORE_NAME(a)\n",
      "\n",
      "1042:  144      1: EXTENDED_ARG()\n",
      "1044:  100    259: LOAD_CONST(259)\n",
      "1046:   90      0: STORE_NAME(a)\n",
      "1048:  144      1: EXTENDED_ARG()\n",
      "1050:  100    260: LOAD_CONST(None)\n",
      "1052:   83      -: RETURN_VALUE()\n"
     ]
    }
   ],
   "source": [
    "source = ''.join('a={}\\n'.format(i) for i in range(260))\n",
    "code = compile(source, '<file>', 'exec')\n",
    "\n",
    "print(90, dis.opname[90])\n",
    "print(100, dis.opname[100])\n",
    "print(144, dis.opname[144])\n",
    "print()\n",
    "\n",
    "print(list(code.co_code))\n",
    "print_dis(code)"
   ]
  },
  {
   "cell_type": "markdown",
   "metadata": {},
   "source": [
    "### Summary\n",
    "In case the argument doesn't fit in a single byte, a special `EXTENDED_ARG` operation is prepended. It supplies a byte's worth of extra data to the next instruction."
   ]
  },
  {
   "cell_type": "markdown",
   "metadata": {},
   "source": [
    "---\n",
    "# Extra section II - Different Kinds of Variables"
   ]
  },
  {
   "cell_type": "code",
   "execution_count": 12,
   "metadata": {
    "collapsed": true
   },
   "outputs": [],
   "source": [
    "def print_dis(code):\n",
    "    line_starts = [a for a, b in dis.findlinestarts(code)]\n",
    "    for instr in dis.get_instructions(code):\n",
    "        if instr.offset in line_starts:\n",
    "            print()\n",
    "        print('{i.offset:2}:  {i.opcode:3} {arg:>6}: {i.opname}({i.argrepr})'.format(\n",
    "                i=instr,\n",
    "                arg='-' if instr.arg is None else instr.arg))\n",
    "\n",
    "def dump_code_attrs(code):\n",
    "    print(code)\n",
    "    for attr_name in dir(code):\n",
    "        if not attr_name.startswith('__'):\n",
    "            print('  {}: {}'.format(attr_name, getattr(code, attr_name)))\n"
   ]
  },
  {
   "cell_type": "code",
   "execution_count": 13,
   "metadata": {
    "collapsed": false
   },
   "outputs": [
    {
     "name": "stdout",
     "output_type": "stream",
     "text": [
      "     1\ta = 3\r\n",
      "     2\tb = 'Hello '\r\n",
      "     3\tprint(a * b)\r\n",
      "     4\t\r\n",
      "     5\tdef func(a=1, *b, **c):\r\n",
      "     6\t    return 7 + 3\r\n"
     ]
    }
   ],
   "source": [
    "!cat -n module.py"
   ]
  },
  {
   "cell_type": "code",
   "execution_count": 14,
   "metadata": {
    "collapsed": false
   },
   "outputs": [
    {
     "name": "stdout",
     "output_type": "stream",
     "text": [
      "<code object <module> at 0x7fbc842cba00, file \"/home/pviktori/dev/slides/2016-06-22-pysilesia-bytecode/module.py\", line 1>\n",
      "  co_argcount: 0\n",
      "  co_cellvars: ()\n",
      "  co_code: b'd\\x00Z\\x00d\\x01Z\\x01e\\x02e\\x00e\\x01\\x14\\x00\\x83\\x01\\x01\\x00d\\x06d\\x03d\\x04\\x84\\x01Z\\x03d\\x05S\\x00'\n",
      "  co_consts: (3, 'Hello ', 1, <code object func at 0x7fbc842cbc40, file \"/home/pviktori/dev/slides/2016-06-22-pysilesia-bytecode/module.py\", line 5>, 'func', None, (1,))\n",
      "  co_filename: /home/pviktori/dev/slides/2016-06-22-pysilesia-bytecode/module.py\n",
      "  co_firstlineno: 1\n",
      "  co_flags: 64\n",
      "  co_freevars: ()\n",
      "  co_kwonlyargcount: 0\n",
      "  co_lnotab: b'\\x04\\x01\\x04\\x01\\x0c\\x02'\n",
      "  co_name: <module>\n",
      "  co_names: ('a', 'b', 'print', 'func')\n",
      "  co_nlocals: 0\n",
      "  co_stacksize: 3\n",
      "  co_varnames: ()\n",
      "\n",
      "Name:              <module>\n",
      "Filename:          /home/pviktori/dev/slides/2016-06-22-pysilesia-bytecode/module.py\n",
      "Argument count:    0\n",
      "Kw-only arguments: 0\n",
      "Number of locals:  0\n",
      "Stack size:        3\n",
      "Flags:             NOFREE\n",
      "Constants:\n",
      "   0: 3\n",
      "   1: 'Hello '\n",
      "   2: 1\n",
      "   3: <code object func at 0x7fbc842cbc40, file \"/home/pviktori/dev/slides/2016-06-22-pysilesia-bytecode/module.py\", line 5>\n",
      "   4: 'func'\n",
      "   5: None\n",
      "   6: (1,)\n",
      "Names:\n",
      "   0: a\n",
      "   1: b\n",
      "   2: print\n",
      "   3: func\n",
      "\n",
      " 0:  100      0: LOAD_CONST(3)\n",
      " 2:   90      0: STORE_NAME(a)\n",
      "\n",
      " 4:  100      1: LOAD_CONST('Hello ')\n",
      " 6:   90      1: STORE_NAME(b)\n",
      "\n",
      " 8:  101      2: LOAD_NAME(print)\n",
      "10:  101      0: LOAD_NAME(a)\n",
      "12:  101      1: LOAD_NAME(b)\n",
      "14:   20      -: BINARY_MULTIPLY()\n",
      "16:  131      1: CALL_FUNCTION(1 positional, 0 keyword pair)\n",
      "18:    1      -: POP_TOP()\n",
      "\n",
      "20:  100      6: LOAD_CONST((1,))\n",
      "22:  100      3: LOAD_CONST(<code object func at 0x7fbc842cbc40, file \"/home/pviktori/dev/slides/2016-06-22-pysilesia-bytecode/module.py\", line 5>)\n",
      "24:  100      4: LOAD_CONST('func')\n",
      "26:  132      1: MAKE_FUNCTION()\n",
      "28:   90      3: STORE_NAME(func)\n",
      "30:  100      5: LOAD_CONST(None)\n",
      "32:   83      -: RETURN_VALUE()\n"
     ]
    }
   ],
   "source": [
    "filename = os.path.abspath('module.py')\n",
    "with open(filename) as f:\n",
    "    code = compile(f.read(), filename=filename, mode='exec')\n",
    "\n",
    "dump_code_attrs(code)\n",
    "print()\n",
    "print(dis.code_info(code))\n",
    "print_dis(code)"
   ]
  },
  {
   "cell_type": "code",
   "execution_count": 15,
   "metadata": {
    "collapsed": false
   },
   "outputs": [
    {
     "name": "stdout",
     "output_type": "stream",
     "text": [
      "<code object repeat_string at 0x7fbc842cb640, file \"<ipython-input-15-3410d72e56a2>\", line 2>\n",
      "  co_argcount: 1\n",
      "  co_cellvars: ()\n",
      "  co_code: b'd\\x01}\\x01|\\x00t\\x00\\x14\\x00|\\x01\\x14\\x00S\\x00'\n",
      "  co_consts: (None, 'hello')\n",
      "  co_filename: <ipython-input-15-3410d72e56a2>\n",
      "  co_firstlineno: 2\n",
      "  co_flags: 67\n",
      "  co_freevars: ()\n",
      "  co_kwonlyargcount: 0\n",
      "  co_lnotab: b'\\x00\\x01\\x04\\x01'\n",
      "  co_name: repeat_string\n",
      "  co_names: ('n',)\n",
      "  co_nlocals: 2\n",
      "  co_stacksize: 2\n",
      "  co_varnames: ('a', 'b')\n",
      "\n",
      "Name:              repeat_string\n",
      "Filename:          <ipython-input-15-3410d72e56a2>\n",
      "Argument count:    1\n",
      "Kw-only arguments: 0\n",
      "Number of locals:  2\n",
      "Stack size:        2\n",
      "Flags:             OPTIMIZED, NEWLOCALS, NOFREE\n",
      "Constants:\n",
      "   0: None\n",
      "   1: 'hello'\n",
      "Names:\n",
      "   0: n\n",
      "Variable names:\n",
      "   0: a\n",
      "   1: b\n",
      "\n",
      " 0:  100      1: LOAD_CONST('hello')\n",
      " 2:  125      1: STORE_FAST(b)\n",
      "\n",
      " 4:  124      0: LOAD_FAST(a)\n",
      " 6:  116      0: LOAD_GLOBAL(n)\n",
      " 8:   20      -: BINARY_MULTIPLY()\n",
      "10:  124      1: LOAD_FAST(b)\n",
      "12:   20      -: BINARY_MULTIPLY()\n",
      "14:   83      -: RETURN_VALUE()\n"
     ]
    }
   ],
   "source": [
    "n = 3\n",
    "def repeat_string(a):\n",
    "    b = 'hello'\n",
    "    return a * n * b\n",
    "\n",
    "dump_code_attrs(repeat_string.__code__)\n",
    "print()\n",
    "print(dis.code_info(repeat_string.__code__))\n",
    "print_dis(repeat_string.__code__)"
   ]
  },
  {
   "cell_type": "code",
   "execution_count": null,
   "metadata": {
    "collapsed": false
   },
   "outputs": [],
   "source": [
    "a = 3\n",
    "def make_class():\n",
    "    class SomeClass:\n",
    "        b = 'hello'\n",
    "        print(a * b)\n",
    "\n",
    "consts = make_class.__code__.co_consts\n",
    "print(dict(enumerate(type(t).__name__ for t in consts)))\n",
    "\n",
    "class_code = consts[1]\n",
    "print()\n",
    "dump_code_attrs(class_code)\n",
    "print()\n",
    "print(dis.code_info(class_code))\n",
    "print_dis(class_code)"
   ]
  },
  {
   "cell_type": "markdown",
   "metadata": {},
   "source": [
    "### Summary\n",
    "There are several different kinds of variables:\n",
    "\n",
    "* Named variables, which are always looked up by name. Module-level code uses these, and they're also used by class code.\n",
    "* Global variables, which are looked up by name in the global (module) namespace. Functions and classes use these when needed.\n",
    "* \"Fast local\" variables, which are accessed by index, so the access is very fast. Functions use these. This means functions need to know all names of variables at compile time, which is why `import *` is not allowed in functions.\n",
    "* (There are also cell variables, which are used in closures to access the outer namespace.)"
   ]
  },
  {
   "cell_type": "code",
   "execution_count": 16,
   "metadata": {
    "collapsed": false
   },
   "outputs": [
    {
     "name": "stdout",
     "output_type": "stream",
     "text": [
      "Hello Hello Hello \n"
     ]
    }
   ],
   "source": [
    "import module"
   ]
  },
  {
   "cell_type": "code",
   "execution_count": 17,
   "metadata": {
    "collapsed": false
   },
   "outputs": [
    {
     "data": {
      "text/plain": [
       "{'__builtins__': {'ArithmeticError': ArithmeticError,\n",
       "  'AssertionError': AssertionError,\n",
       "  'AttributeError': AttributeError,\n",
       "  'BaseException': BaseException,\n",
       "  'BlockingIOError': BlockingIOError,\n",
       "  'BrokenPipeError': BrokenPipeError,\n",
       "  'BufferError': BufferError,\n",
       "  'BytesWarning': BytesWarning,\n",
       "  'ChildProcessError': ChildProcessError,\n",
       "  'ConnectionAbortedError': ConnectionAbortedError,\n",
       "  'ConnectionError': ConnectionError,\n",
       "  'ConnectionRefusedError': ConnectionRefusedError,\n",
       "  'ConnectionResetError': ConnectionResetError,\n",
       "  'DeprecationWarning': DeprecationWarning,\n",
       "  'EOFError': EOFError,\n",
       "  'Ellipsis': Ellipsis,\n",
       "  'EnvironmentError': OSError,\n",
       "  'Exception': Exception,\n",
       "  'False': False,\n",
       "  'FileExistsError': FileExistsError,\n",
       "  'FileNotFoundError': FileNotFoundError,\n",
       "  'FloatingPointError': FloatingPointError,\n",
       "  'FutureWarning': FutureWarning,\n",
       "  'GeneratorExit': GeneratorExit,\n",
       "  'IOError': OSError,\n",
       "  'ImportError': ImportError,\n",
       "  'ImportWarning': ImportWarning,\n",
       "  'IndentationError': IndentationError,\n",
       "  'IndexError': IndexError,\n",
       "  'InterruptedError': InterruptedError,\n",
       "  'IsADirectoryError': IsADirectoryError,\n",
       "  'KeyError': KeyError,\n",
       "  'KeyboardInterrupt': KeyboardInterrupt,\n",
       "  'LookupError': LookupError,\n",
       "  'MemoryError': MemoryError,\n",
       "  'NameError': NameError,\n",
       "  'None': None,\n",
       "  'NotADirectoryError': NotADirectoryError,\n",
       "  'NotImplemented': NotImplemented,\n",
       "  'NotImplementedError': NotImplementedError,\n",
       "  'OSError': OSError,\n",
       "  'OverflowError': OverflowError,\n",
       "  'PendingDeprecationWarning': PendingDeprecationWarning,\n",
       "  'PermissionError': PermissionError,\n",
       "  'ProcessLookupError': ProcessLookupError,\n",
       "  'RecursionError': RecursionError,\n",
       "  'ReferenceError': ReferenceError,\n",
       "  'ResourceWarning': ResourceWarning,\n",
       "  'RuntimeError': RuntimeError,\n",
       "  'RuntimeWarning': RuntimeWarning,\n",
       "  'StopAsyncIteration': StopAsyncIteration,\n",
       "  'StopIteration': StopIteration,\n",
       "  'SyntaxError': SyntaxError,\n",
       "  'SyntaxWarning': SyntaxWarning,\n",
       "  'SystemError': SystemError,\n",
       "  'SystemExit': SystemExit,\n",
       "  'TabError': TabError,\n",
       "  'TimeoutError': TimeoutError,\n",
       "  'True': True,\n",
       "  'TypeError': TypeError,\n",
       "  'UnboundLocalError': UnboundLocalError,\n",
       "  'UnicodeDecodeError': UnicodeDecodeError,\n",
       "  'UnicodeEncodeError': UnicodeEncodeError,\n",
       "  'UnicodeError': UnicodeError,\n",
       "  'UnicodeTranslateError': UnicodeTranslateError,\n",
       "  'UnicodeWarning': UnicodeWarning,\n",
       "  'UserWarning': UserWarning,\n",
       "  'ValueError': ValueError,\n",
       "  'Warning': Warning,\n",
       "  'ZeroDivisionError': ZeroDivisionError,\n",
       "  '__IPYTHON__': True,\n",
       "  '__IPYTHON__active': 'Deprecated, check for __IPYTHON__',\n",
       "  '__build_class__': <function __build_class__>,\n",
       "  '__debug__': True,\n",
       "  '__doc__': \"Built-in functions, exceptions, and other objects.\\n\\nNoteworthy: None is the `nil' object; Ellipsis represents `...' in slices.\",\n",
       "  '__import__': <function __import__>,\n",
       "  '__loader__': _frozen_importlib.BuiltinImporter,\n",
       "  '__name__': 'builtins',\n",
       "  '__package__': '',\n",
       "  '__spec__': ModuleSpec(name='builtins', loader=<class '_frozen_importlib.BuiltinImporter' at 0x1d0c088>),\n",
       "  'abs': <function abs>,\n",
       "  'all': <function all>,\n",
       "  'any': <function any>,\n",
       "  'ascii': <function ascii>,\n",
       "  'bin': <function bin>,\n",
       "  'bool': bool,\n",
       "  'bytearray': bytearray,\n",
       "  'bytes': bytes,\n",
       "  'callable': <function callable>,\n",
       "  'chr': <function chr>,\n",
       "  'classmethod': classmethod,\n",
       "  'compile': <function compile>,\n",
       "  'complex': complex,\n",
       "  'copyright': Copyright (c) 2001-2016 Python Software Foundation.\n",
       "  All Rights Reserved.\n",
       "  \n",
       "  Copyright (c) 2000 BeOpen.com.\n",
       "  All Rights Reserved.\n",
       "  \n",
       "  Copyright (c) 1995-2001 Corporation for National Research Initiatives.\n",
       "  All Rights Reserved.\n",
       "  \n",
       "  Copyright (c) 1991-1995 Stichting Mathematisch Centrum, Amsterdam.\n",
       "  All Rights Reserved.,\n",
       "  'credits':     Thanks to CWI, CNRI, BeOpen.com, Zope Corporation and a cast of thousands\n",
       "      for supporting Python development.  See www.python.org for more information.,\n",
       "  'delattr': <function delattr>,\n",
       "  'dict': dict,\n",
       "  'dir': <function dir>,\n",
       "  'divmod': <function divmod>,\n",
       "  'dreload': <function IPython.lib.deepreload._dreload>,\n",
       "  'enumerate': enumerate,\n",
       "  'eval': <function eval>,\n",
       "  'exec': <function exec>,\n",
       "  'filter': filter,\n",
       "  'float': float,\n",
       "  'format': <function format>,\n",
       "  'frozenset': frozenset,\n",
       "  'get_ipython': <bound method InteractiveShell.get_ipython of <ipykernel.zmqshell.ZMQInteractiveShell object at 0x7fbc85c4f7a8>>,\n",
       "  'getattr': <function getattr>,\n",
       "  'globals': <function globals>,\n",
       "  'hasattr': <function hasattr>,\n",
       "  'hash': <function hash>,\n",
       "  'help': Type help() for interactive help, or help(object) for help about object.,\n",
       "  'hex': <function hex>,\n",
       "  'id': <function id>,\n",
       "  'input': <bound method Kernel.raw_input of <ipykernel.ipkernel.IPythonKernel object at 0x7fbc85c4f740>>,\n",
       "  'int': int,\n",
       "  'isinstance': <function isinstance>,\n",
       "  'issubclass': <function issubclass>,\n",
       "  'iter': <function iter>,\n",
       "  'len': <function len>,\n",
       "  'license': Type license() to see the full license text,\n",
       "  'list': list,\n",
       "  'locals': <function locals>,\n",
       "  'map': map,\n",
       "  'max': <function max>,\n",
       "  'memoryview': memoryview,\n",
       "  'min': <function min>,\n",
       "  'next': <function next>,\n",
       "  'object': object,\n",
       "  'oct': <function oct>,\n",
       "  'open': <function io.open>,\n",
       "  'ord': <function ord>,\n",
       "  'pow': <function pow>,\n",
       "  'print': <function print>,\n",
       "  'property': property,\n",
       "  'range': range,\n",
       "  'repr': <function repr>,\n",
       "  'reversed': reversed,\n",
       "  'round': <function round>,\n",
       "  'set': set,\n",
       "  'setattr': <function setattr>,\n",
       "  'slice': slice,\n",
       "  'sorted': <function sorted>,\n",
       "  'staticmethod': staticmethod,\n",
       "  'str': str,\n",
       "  'sum': <function sum>,\n",
       "  'super': super,\n",
       "  'tuple': tuple,\n",
       "  'type': type,\n",
       "  'vars': <function vars>,\n",
       "  'zip': zip},\n",
       " '__cached__': '/home/pviktori/dev/slides/2016-06-22-pysilesia-bytecode/__pycache__/module.cpython-36.pyc',\n",
       " '__doc__': None,\n",
       " '__file__': '/home/pviktori/dev/slides/2016-06-22-pysilesia-bytecode/module.py',\n",
       " '__loader__': <_frozen_importlib_external.SourceFileLoader at 0x7fbc84296d58>,\n",
       " '__name__': 'module',\n",
       " '__package__': '',\n",
       " '__spec__': ModuleSpec(name='module', loader=<_frozen_importlib_external.SourceFileLoader object at 0x7fbc84296d58>, origin='/home/pviktori/dev/slides/2016-06-22-pysilesia-bytecode/module.py'),\n",
       " 'a': 3,\n",
       " 'b': 'Hello ',\n",
       " 'func': <function module.func>}"
      ]
     },
     "execution_count": 17,
     "metadata": {},
     "output_type": "execute_result"
    }
   ],
   "source": [
    "module.__dict__"
   ]
  },
  {
   "cell_type": "code",
   "execution_count": 21,
   "metadata": {
    "collapsed": false
   },
   "outputs": [],
   "source": [
    "module.func.__globals__['f'] = 3"
   ]
  },
  {
   "cell_type": "code",
   "execution_count": 22,
   "metadata": {
    "collapsed": false
   },
   "outputs": [
    {
     "data": {
      "text/plain": [
       "3"
      ]
     },
     "execution_count": 22,
     "metadata": {},
     "output_type": "execute_result"
    }
   ],
   "source": [
    "module.f"
   ]
  },
  {
   "cell_type": "code",
   "execution_count": 23,
   "metadata": {
    "collapsed": false
   },
   "outputs": [
    {
     "data": {
      "text/plain": [
       "3"
      ]
     },
     "execution_count": 23,
     "metadata": {},
     "output_type": "execute_result"
    }
   ],
   "source": [
    "module.__dict__['f']"
   ]
  },
  {
   "cell_type": "code",
   "execution_count": 27,
   "metadata": {
    "collapsed": false
   },
   "outputs": [],
   "source": [
    "class Foo:\n",
    "    ...\n",
    "\n",
    "Foo.f = 123\n",
    "Foo.__add__ = lambda self, other: self + other"
   ]
  },
  {
   "cell_type": "code",
   "execution_count": 33,
   "metadata": {
    "collapsed": false
   },
   "outputs": [],
   "source": [
    "dct = {'a': 1, 'b': 2}\n",
    "yeah = type(Foo.__dict__)(dct)"
   ]
  },
  {
   "cell_type": "code",
   "execution_count": 32,
   "metadata": {
    "collapsed": false
   },
   "outputs": [
    {
     "data": {
      "text/plain": [
       "1"
      ]
     },
     "execution_count": 32,
     "metadata": {},
     "output_type": "execute_result"
    }
   ],
   "source": [
    "yeah['a']"
   ]
  },
  {
   "cell_type": "code",
   "execution_count": 34,
   "metadata": {
    "collapsed": false
   },
   "outputs": [
    {
     "data": {
      "text/plain": [
       "6"
      ]
     },
     "execution_count": 34,
     "metadata": {},
     "output_type": "execute_result"
    }
   ],
   "source": [
    "dct[5] = 6\n",
    "yeah[5]"
   ]
  },
  {
   "cell_type": "code",
   "execution_count": 36,
   "metadata": {
    "collapsed": false
   },
   "outputs": [
    {
     "data": {
      "text/plain": [
       "9"
      ]
     },
     "execution_count": 36,
     "metadata": {},
     "output_type": "execute_result"
    }
   ],
   "source": [
    "type(4)(\"9\")"
   ]
  },
  {
   "cell_type": "code",
   "execution_count": null,
   "metadata": {
    "collapsed": true
   },
   "outputs": [],
   "source": []
  }
 ],
 "metadata": {
  "kernelspec": {
   "display_name": "Python 3",
   "language": "python",
   "name": "python3"
  },
  "language_info": {
   "codemirror_mode": {
    "name": "ipython",
    "version": 3
   },
   "file_extension": ".py",
   "mimetype": "text/x-python",
   "name": "python",
   "nbconvert_exporter": "python",
   "pygments_lexer": "ipython3",
   "version": "3.6.0a2+"
  }
 },
 "nbformat": 4,
 "nbformat_minor": 0
}
